run11/__init__.py
run11-2025.0.1.dist-info/licenses/LICENSE
run11-2025.0.1.dist-info/METADATA
run11-2025.0.1.dist-info/WHEEL
run11-2025.0.1.dist-info/entry_points.txt
run11-2025.0.1.dist-info/top_level.txt
run11-2025.0.1.dist-info/RECORD
