Metadata-Version: 2.4
Name: run11
Version: 2025.0.1
Summary: Run11 by DeeBeeBros.com makes terminal life easiee
Author-email: "Victor G.B. Peters" <victor@jeex.eu>
Project-URL: Homepage, https://deebeebros.com
Project-URL: Issues, https://deebeebros.com/contact
Classifier: Programming Language :: Python :: 3
Classifier: License :: OSI Approved :: MIT License
Classifier: Operating System :: OS Independent
Requires-Python: >=3.11
License-File: LICENSE
Requires-Dist: PyYAML
Requires-Dist: colorama
Requires-Dist: requests
Requires-Dist: pytz
Requires-Dist: paramiko
Dynamic: license-file
